<annotation>
	<folder>train</folder>
	<filename>42.jpg</filename>
	<path>E:\Matheus\MachineLearning\QUALIDADE_AR_ACI\TREINAR_COLAB\data\images\train\42.jpg</path>
	<source>
		<database>Unknown</database>
	</source>
	<size>
		<width>800</width>
		<height>600</height>
		<depth>3</depth>
	</size>
	<segmented>0</segmented>
	<object>
		<name>ruim</name>
		<pose>Unspecified</pose>
		<truncated>0</truncated>
		<difficult>0</difficult>
		<bndbox>
			<xmin>33</xmin>
			<ymin>2</ymin>
			<xmax>288</xmax>
			<ymax>119</ymax>
		</bndbox>
	</object>
	<object>
		<name>bom</name>
		<pose>Unspecified</pose>
		<truncated>0</truncated>
		<difficult>0</difficult>
		<bndbox>
			<xmin>308</xmin>
			<ymin>32</ymin>
			<xmax>723</xmax>
			<ymax>425</ymax>
		</bndbox>
	</object>
</annotation>
