<annotation>
	<folder>train</folder>
	<filename>a (156).jpg</filename>
	<path>E:\Matheus\MachineLearning\QUALIDADE_AR_ACI\TREINAR_COLAB\data\images\train\a (156).jpg</path>
	<source>
		<database>Unknown</database>
	</source>
	<size>
		<width>800</width>
		<height>600</height>
		<depth>3</depth>
	</size>
	<segmented>0</segmented>
	<object>
		<name>ruim</name>
		<pose>Unspecified</pose>
		<truncated>0</truncated>
		<difficult>0</difficult>
		<bndbox>
			<xmin>431</xmin>
			<ymin>175</ymin>
			<xmax>704</xmax>
			<ymax>491</ymax>
		</bndbox>
	</object>
	<object>
		<name>bom</name>
		<pose>Unspecified</pose>
		<truncated>0</truncated>
		<difficult>0</difficult>
		<bndbox>
			<xmin>18</xmin>
			<ymin>2</ymin>
			<xmax>294</xmax>
			<ymax>132</ymax>
		</bndbox>
	</object>
</annotation>
