<annotation>
	<folder>train</folder>
	<filename>aaaaa (34).jpg</filename>
	<path>E:\Matheus\MachineLearning\QUALIDADE_AR_ACI\TREINAR_COLAB\data\images\train\aaaaa (34).jpg</path>
	<source>
		<database>Unknown</database>
	</source>
	<size>
		<width>800</width>
		<height>600</height>
		<depth>3</depth>
	</size>
	<segmented>0</segmented>
	<object>
		<name>bom</name>
		<pose>Unspecified</pose>
		<truncated>0</truncated>
		<difficult>0</difficult>
		<bndbox>
			<xmin>4</xmin>
			<ymin>5</ymin>
			<xmax>268</xmax>
			<ymax>161</ymax>
		</bndbox>
	</object>
	<object>
		<name>bom</name>
		<pose>Unspecified</pose>
		<truncated>0</truncated>
		<difficult>0</difficult>
		<bndbox>
			<xmin>227</xmin>
			<ymin>41</ymin>
			<xmax>598</xmax>
			<ymax>407</ymax>
		</bndbox>
	</object>
	<object>
		<name>ruim</name>
		<pose>Unspecified</pose>
		<truncated>1</truncated>
		<difficult>0</difficult>
		<bndbox>
			<xmin>614</xmin>
			<ymin>237</ymin>
			<xmax>800</xmax>
			<ymax>481</ymax>
		</bndbox>
	</object>
</annotation>
